meta_mcp/__init__.py
meta_mcp/main.py
meta_mcp/mcp.py
meta_mcp/utils.py
meta_mcp/tools/__init__.py
meta_mcp/tools/_call.py
meta_mcp/tools/_search.py
biocontext_meta-0.1.0.dist-info/METADATA
biocontext_meta-0.1.0.dist-info/WHEEL
biocontext_meta-0.1.0.dist-info/entry_points.txt
biocontext_meta-0.1.0.dist-info/licenses/LICENSE
biocontext_meta-0.1.0.dist-info/RECORD
