Metadata-Version: 2.4
Name: biocontext-meta
Version: 0.1.0
Summary: The BioContext AI meta mcp enables access to all installable MCP servers in the BioContextAI registry with minimal context consumption.
Project-URL: Documentation, https://meta-mcp.readthedocs.io/
Project-URL: Homepage, https://github.com/biocontext-ai/meta-mcp
Project-URL: Source, https://github.com/biocontext-ai/meta-mcp
Author: Darius Schaub
Maintainer-email: Darius Schaub <schaub.darius@gmail.com>
License: 
License-File: LICENSE
Classifier: Programming Language :: Python :: 3 :: Only
Classifier: Programming Language :: Python :: 3.11
Classifier: Programming Language :: Python :: 3.12
Classifier: Programming Language :: Python :: 3.13
Requires-Python: >=3.11
Requires-Dist: click>=8.3.1
Requires-Dist: fastmcp<3
Requires-Dist: httpx<1
Requires-Dist: json-schema-to-pydantic>=0.4.7
Requires-Dist: litellm>=1.80.7
Requires-Dist: numpy>=2.4.1
Requires-Dist: pandas>=2.3.3
Requires-Dist: rapidfuzz>=3.14.3
Requires-Dist: sentence-transformers>=5.2.0
Provides-Extra: dev
Requires-Dist: jupyter; extra == 'dev'
Requires-Dist: pre-commit; extra == 'dev'
Requires-Dist: twine>=4.0.2; extra == 'dev'
Provides-Extra: doc
Requires-Dist: docutils!=0.18.*,!=0.19.*,>=0.8; extra == 'doc'
Requires-Dist: ipykernel; extra == 'doc'
Requires-Dist: ipython; extra == 'doc'
Requires-Dist: myst-nb>=1.1; extra == 'doc'
Requires-Dist: pandas; extra == 'doc'
Requires-Dist: setuptools; extra == 'doc'
Requires-Dist: sphinx-autoapi; extra == 'doc'
Requires-Dist: sphinx-book-theme>=1; extra == 'doc'
Requires-Dist: sphinx-copybutton; extra == 'doc'
Requires-Dist: sphinx-tabs; extra == 'doc'
Requires-Dist: sphinx>=8.1; extra == 'doc'
Requires-Dist: sphinxext-opengraph; extra == 'doc'
Provides-Extra: test
Requires-Dist: anndata; extra == 'test'
Requires-Dist: coverage; extra == 'test'
Requires-Dist: pytest; extra == 'test'
Requires-Dist: pytest-asyncio; extra == 'test'
